UploadGarmin
ez_setup
