Metadata-Version: 1.1
Name: GcpUploader
Version: 2015.2.28
Summary: A tool to upload FIT, GPX, and TCX files to the Garmin Connect web site.
Home-page: http://sourceforge.net/projects/gcpuploader/
Author: David E. Lotton
Author-email: yellow56@gmail.com
License: GPL
Keywords: GARMIN CONNECT GPS TCX GPX FIT UPLOAD UPLOADER
Platform: UNKNOWN
Classifier: Development Status :: 3 - Alpha
Classifier: Environment :: Console
Classifier: Intended Audience :: End Users/Desktop
Classifier: License :: OSI Approved :: GNU General Public License (GPL)
Classifier: Programming Language :: Python
Classifier: Topic :: Utilities
